{
  "header": "Webbi Kauppa Sovellus",
  "categories": {
    "electronics": "Elektroniikka",
    "jewelery": "Korut",
    "mens-clothing": "Miesten vaatteet",
    "womens-clothing": "Naisten vaatteet"
  },
  "general": {
    "loading": "Ladataan"
  },
  "product-info": {
    "brand": "Br채ndi",
    "rated": "Arvostelu",
    "option": "Vaihtoehto",
    "type": "Tyyppi",
    "stock-available": "Varastossa",
    "out-of-stock": "Loppu varastosta",
    "add-to-cart": "Lis채채 koriin",
    "sold-by": "Myyj채"
  }
}
